teflow/__init__.py
teflow/__main__.py
teflow/_version.py
teflow/anisotro.py
teflow/bandlib.py
teflow/engout.py
teflow/interface.py
teflow/kappa.py
teflow/loader.py
teflow/mathext.py
teflow/utils.py
teflow/ztdev.py
teflow-0.4.6.dist-info/LICENSE
teflow-0.4.6.dist-info/METADATA
teflow-0.4.6.dist-info/WHEEL
teflow-0.4.6.dist-info/entry_points.txt
teflow-0.4.6.dist-info/top_level.txt
teflow-0.4.6.dist-info/RECORD
