Metadata-Version: 2.1
Name: TEflow
Version: 0.4.6
Summary: A python3 package for thermoelectric output performance calculations
Home-page: https://github.com/JianboHIT/TEflow
Author: Jianbo ZHU
License: Apache-2.0 license
Keywords: thermoelectricity,simulation
Classifier: Development Status :: 3 - Alpha
Classifier: Programming Language :: Python :: 3
Classifier: Programming Language :: Python :: 3.8
Classifier: Topic :: Scientific/Engineering
Classifier: Intended Audience :: Science/Research
Classifier: License :: OSI Approved :: Apache Software License
License-File: LICENSE
Requires-Dist: numpy
Requires-Dist: scipy
